tt4human/__init__.py
tt4human/_version.py
tt4human/api.py
tt4human/better_enum.py
tt4human/compat.py
tt4human/core.py
tt4human/paths.py
tt4human/docs/__init__.py
tt4human/tests/__init__.py
tt4human/tests/helper.py
tt4human/vendor/__init__.py
tt4human/vendor/pytest_cov_helper.py
tt4human/vendor/strutils.py
tt4human-0.3.1.dist-info/AUTHORS.rst
tt4human-0.3.1.dist-info/LICENSE.txt
tt4human-0.3.1.dist-info/METADATA
tt4human-0.3.1.dist-info/WHEEL
tt4human-0.3.1.dist-info/top_level.txt
tt4human-0.3.1.dist-info/RECORD
